Workbook

Sheet dataset
A1: Date | B1: Employee | C1: Region | D1: Product | E1: Category | F1: Sales | G1: Cost | H1: Profit | I1: MONTH | Q1: Employee | R1: Sum of Profit
A2: 46023 | B2: Rahul | C2: South | D2: Laptop | E2: Electronics | F2: 45000 | G2: 30000 | H2: 15000 | I2: =TEXT(Table2[[#This Row],[Date]],"mmm-yyyy") -> Jan-2026 | M2: ANALYSIS | Q2: Arjun | R2: 60700
A3: 46024 | B3: Priya | C3: North | D3: Phone | E3: Electronics | F3: 30000 | G3: 21000 | H3: 9000 | I3: =TEXT(Table2[[#This Row],[Date]],"mmm-yyyy") -> Jan-2026 | M3: Total sales= | N3: =SUM(Table2[Sales]) -> 1231700 | Q3: Kiran | R3: 60800
A4: 46025 | B4: Arjun | C4: East | D4: Tablet | E4: Electronics | F4: 25000 | G4: 17000 | H4: 8000 | I4: =TEXT(Table2[[#This Row],[Date]],"mmm-yyyy") -> Jan-2026 | M4: Total cost= | N4: =SUM(Table2[Cost]) -> 818000 | Q4: Priya | R4: 93300
A5: 46026 | B5: Sneha | C5: West | D5: Monitor | E5: Electronics | F5: 22000 | G5: 15000 | H5: 7000 | I5: =TEXT(Table2[[#This Row],[Date]],"mmm-yyyy") -> Jan-2026 | M5: Total Profit= | N5: =SUM(Table2[Profit]) -> 413700 | Q5: Rahul | R5: 105700
A6: 46027 | B6: Kiran | C6: South | D6: Keyboard | E6: Accessories | F6: 5000 | G6: 3000 | H6: 2000 | I6: =TEXT(Table2[[#This Row],[Date]],"mmm-yyyy") -> Jan-2026 | M6: Profit Margin | N6: =(N5/N3)*100 -> 33.587724 | Q6: Sneha | R6: 93200
A7: 46028 | B7: Rahul | C7: North | D7: Mouse | E7: Accessories | F7: 3000 | G7: 1800 | H7: 1200 | I7: =TEXT(Table2[[#This Row],[Date]],"mmm-yyyy") -> Jan-2026 | M7: Count of sales | N7: =COUNT(Table2[Date]) -> 51 | Q7: Grand Total | R7: 413700
A8: 46029 | B8: Priya | C8: East | D8: Laptop | E8: Electronics | F8: 48000 | G8: 32000 | H8: 16000 | I8: =TEXT(Table2[[#This Row],[Date]],"mmm-yyyy") -> Jan-2026 | M8: Avergae Sales= | N8: =AVERAGE(Table2[Sales]) -> 24150.98
A9: 46030 | B9: Arjun | C9: West | D9: Headphones | E9: Accessories | F9: 7000 | G9: 4000 | H9: 3000 | I9: =TEXT(Table2[[#This Row],[Date]],"mmm-yyyy") -> Jan-2026
A10: 46031 | B10: Sneha | C10: South | D10: Phone | E10: Electronics | F10: 35000 | G10: 24000 | H10: 11000 | I10: =TEXT(Table2[[#This Row],[Date]],"mmm-yyyy") -> Jan-2026 | M10: PRODUCT WISE SALES AND PROFIT
A11: 46032 | B11: Kiran | C11: North | D11: Printer | E11: Office | F11: 18000 | G11: 12000 | H11: 6000 | I11: =TEXT(Table2[[#This Row],[Date]],"mmm-yyyy") -> Jan-2026 | M11: Product | N11: Sum of Sales | O11: Sum of Profit | Q11: MONTHLY SALES
A12: 46033 | B12: Rahul | C12: East | D12: Monitor | E12: Electronics | F12: 24000 | G12: 16000 | H12: 8000 | I12: =TEXT(Table2[[#This Row],[Date]],"mmm-yyyy") -> Jan-2026 | M12: Headphones | N12: 40000 | O12: 17500 | Q12: MONTH | R12: Sum of Sales
A13: 46034 | B13: Priya | C13: West | D13: Keyboard | E13: Accessories | F13: 5500 | G13: 3200 | H13: 2300 | I13: =TEXT(Table2[[#This Row],[Date]],"mmm-yyyy") -> Jan-2026 | M13: Keyboard | N13: 27500 | O13: 11500 | Q13: Feb-2026 | R13: 503200
A14: 46035 | B14: Arjun | C14: South | D14: Tablet | E14: Electronics | F14: 27000 | G14: 18000 | H14: 9000 | I14: =TEXT(Table2[[#This Row],[Date]],"mmm-yyyy") -> Jan-2026 | M14: Laptop | N14: 391000 | O14: 129000 | Q14: Jan-2026 | R14: 728500
A15: 46036 | B15: Sneha | C15: North | D15: Laptop | E15: Electronics | F15: 52000 | G15: 35000 | H15: 17000 | I15: =TEXT(Table2[[#This Row],[Date]],"mmm-yyyy") -> Jan-2026 | M15: Monitor | N15: 168000 | O15: 55500 | Q15: Grand Total | R15: 1231700
A16: 46037 | B16: Kiran | C16: East | D16: Mouse | E16: Accessories | F16: 3500 | G16: 2000 | H16: 1500 | I16: =TEXT(Table2[[#This Row],[Date]],"mmm-yyyy") -> Jan-2026 | M16: Mouse | N16: 19200 | O16: 8200
A17: 46038 | B17: Rahul | C17: West | D17: Phone | E17: Electronics | F17: 32000 | G17: 22000 | H17: 10000 | I17: =TEXT(Table2[[#This Row],[Date]],"mmm-yyyy") -> Jan-2026 | M17: Phone | N17: 273000 | O17: 87000
A18: 46039 | B18: Priya | C18: South | D18: Printer | E18: Office | F18: 20000 | G18: 13000 | H18: 7000 | I18: =TEXT(Table2[[#This Row],[Date]],"mmm-yyyy") -> Jan-2026 | M18: Printer | N18: 117000 | O18: 41000
A19: 46040 | B19: Arjun | C19: North | D19: Headphones | E19: Accessories | F19: 7500 | G19: 4200 | H19: 3300 | I19: =TEXT(Table2[[#This Row],[Date]],"mmm-yyyy") -> Jan-2026 | M19: Tablet | N19: 196000 | O19: 64000 | Q19: REGION WISE SALES AND PROFIT
A20: 46041 | B20: Sneha | C20: East | D20: Laptop | E20: Electronics | F20: 46000 | G20: 31000 | H20: 15000 | I20: =TEXT(Table2[[#This Row],[Date]],"mmm-yyyy") -> Jan-2026 | M20: Grand Total | N20: 1231700 | O20: 413700 | Q20: Region | R20: Sum of Sales | S20: Sum of Profit
A21: 46042 | B21: Kiran | C21: West | D21: Monitor | E21: Electronics | F21: 23000 | G21: 15500 | H21: 7500 | I21: =TEXT(Table2[[#This Row],[Date]],"mmm-yyyy") -> Jan-2026 | Q21: East | R21: 339800 | S21: 113000
A22: 46043 | B22: Rahul | C22: South | D22: Tablet | E22: Electronics | F22: 26000 | G22: 17500 | H22: 8500 | I22: =TEXT(Table2[[#This Row],[Date]],"mmm-yyyy") -> Jan-2026 | Q22: North | R22: 263200 | S22: 90000
A23: 46044 | B23: Priya | C23: North | D23: Keyboard | E23: Accessories | F23: 6000 | G23: 3500 | H23: 2500 | I23: =TEXT(Table2[[#This Row],[Date]],"mmm-yyyy") -> Jan-2026 | Q23: South | R23: 340200 | S23: 114700
A24: 46045 | B24: Arjun | C24: East | D24: Phone | E24: Electronics | F24: 34000 | G24: 23000 | H24: 11000 | I24: =TEXT(Table2[[#This Row],[Date]],"mmm-yyyy") -> Jan-2026 | Q24: West | R24: 288500 | S24: 96000
A25: 46046 | B25: Sneha | C25: West | D25: Printer | E25: Office | F25: 19000 | G25: 12500 | H25: 6500 | I25: =TEXT(Table2[[#This Row],[Date]],"mmm-yyyy") -> Jan-2026 | Q25: Grand Total | R25: 1231700 | S25: 413700
A26: 46047 | B26: Kiran | C26: South | D26: Headphones | E26: Accessories | F26: 8000 | G26: 4500 | H26: 3500 | I26: =TEXT(Table2[[#This Row],[Date]],"mmm-yyyy") -> Jan-2026
A27: 46048 | B27: Rahul | C27: North | D27: Laptop | E27: Electronics | F27: 50000 | G27: 33500 | H27: 16500 | I27: =TEXT(Table2[[#This Row],[Date]],"mmm-yyyy") -> Jan-2026
A28: 46049 | B28: Priya | C28: East | D28: Monitor | E28: Electronics | F28: 21000 | G28: 14000 | H28: 7000 | I28: =TEXT(Table2[[#This Row],[Date]],"mmm-yyyy") -> Jan-2026
A29: 46050 | B29: Arjun | C29: West | D29: Mouse | E29: Accessories | F29: 4000 | G29: 2300 | H29: 1700 | I29: =TEXT(Table2[[#This Row],[Date]],"mmm-yyyy") -> Jan-2026
A30: 46051 | B30: Sneha | C30: South | D30: Phone | E30: Electronics | F30: 37000 | G30: 25000 | H30: 12000 | I30: =TEXT(Table2[[#This Row],[Date]],"mmm-yyyy") -> Jan-2026
A31: 46052 | B31: Kiran | C31: North | D31: Tablet | E31: Electronics | F31: 28000 | G31: 19000 | H31: 9000 | I31: =TEXT(Table2[[#This Row],[Date]],"mmm-yyyy") -> Jan-2026
A32: 46053 | B32: Rahul | C32: East | D32: Printer | E32: Office | F32: 17000 | G32: 11000 | H32: 6000 | I32: =TEXT(Table2[[#This Row],[Date]],"mmm-yyyy") -> Jan-2026
A33: 46055 | B33: Priya | C33: West | D33: Laptop | E33: Electronics | F33: 47000 | G33: 31500 | H33: 15500 | I33: =TEXT(Table2[[#This Row],[Date]],"mmm-yyyy") -> Feb-2026
A34: 46056 | B34: Arjun | C34: South | D34: Keyboard | E34: Accessories | F34: 5200 | G34: 3000 | H34: 2200 | I34: =TEXT(Table2[[#This Row],[Date]],"mmm-yyyy") -> Feb-2026
A35: 46057 | B35: Sneha | C35: North | D35: Headphones | E35: Accessories | F35: 8500 | G35: 4800 | H35: 3700 | I35: =TEXT(Table2[[#This Row],[Date]],"mmm-yyyy") -> Feb-2026
A36: 46058 | B36: Kiran | C36: East | D36: Phone | E36: Electronics | F36: 31000 | G36: 21000 | H36: 10000 | I36: =TEXT(Table2[[#This Row],[Date]],"mmm-yyyy") -> Feb-2026
A37: 46059 | B37: Rahul | C37: West | D37: Monitor | E37: Electronics | F37: 25000 | G37: 16500 | H37: 8500 | I37: =TEXT(Table2[[#This Row],[Date]],"mmm-yyyy") -> Feb-2026
... A52: 46074 | B52: Rahul | C52: East | D52: Tablet | E52: Electronics | F52: 31000 | G52: 21000 | H52: 10000 | I52: =TEXT(Table2[[#This Row],[Date]],"mmm-yyyy") -> Feb-2026

Sheet kpi and charts
E1: TOTAL SALES | J1: TOTAL PROFIT | O1: TOTAL COST
E3: =dataset!N3 -> 1231700 | J3: =dataset!N5 -> 413700 | O3: =dataset!N4 -> 818000
E9: PROFIT MARGIN | J9: COUNT | O9: AVERGARE SALES
E11: =dataset!N6 -> 33.587724 | J11: =dataset!N7 -> 51 | O11: =dataset!N8 -> 24150.98
